{
  "generated_at": "2026-01-25T10:08:23.436Z",
  "version": "1.0.0",
  "categories": [
    {
      "id": "test-infrastructure",
      "name": "Test Infrastructure",
      "description": "Test maintenance and reliability",
      "task_count": 4,
      "total_effort_hours": 4.5,
      "tasks": [
        {
          "id": "test-flaky-sxkvsedpv",
          "title": "Fix date boundary issues in heatmap tests",
          "description": "Flaky test at src/__tests__/lib/activity-heatmap.test.ts:144",
          "category": "Test Infrastructure",
          "effort_hours": 1,
          "impact_score": 6,
          "priority": "high",
          "status": "pending",
          "blockers": [],
          "files_affected": [
            "src/__tests__/lib/activity-heatmap.test.ts"
          ],
          "related_docs": [
            "docs/operations/todo.md"
          ],
          "tags": [
            "test",
            "flaky"
          ],
          "created_at": "2025-12-23",
          "last_updated": "2026-01-25"
        },
        {
          "id": "test-flaky-xcmbed7ot",
          "title": "Fix performance tests (environment-dependent, flaky in CI)",
          "description": "Flaky test at src/__tests__/lib/activity-search.test.ts:240",
          "category": "Test Infrastructure",
          "effort_hours": 1,
          "impact_score": 5,
          "priority": "high",
          "status": "pending",
          "blockers": [],
          "files_affected": [
            "src/__tests__/lib/activity-search.test.ts"
          ],
          "related_docs": [
            "docs/operations/todo.md"
          ],
          "tags": [
            "test",
            "flaky"
          ],
          "created_at": "2025-12-23",
          "last_updated": "2026-01-25"
        },
        {
          "id": "test-flaky-i5wgjwnwd",
          "title": "Fix Radix Tabs async behavior in tests",
          "description": "Flaky test at src/__tests__/components/home/trending-section.test.tsx:216",
          "category": "Test Infrastructure",
          "effort_hours": 1.5,
          "impact_score": 6,
          "priority": "high",
          "status": "pending",
          "blockers": [],
          "files_affected": [
            "src/__tests__/components/home/trending-section.test.tsx"
          ],
          "related_docs": [
            "docs/operations/todo.md"
          ],
          "tags": [
            "test",
            "flaky"
          ],
          "created_at": "2025-12-23",
          "last_updated": "2026-01-25"
        },
        {
          "id": "test-flaky-5o9o8lfzu",
          "title": "Fix aria-selected not updating in tests",
          "description": "Flaky test at src/__tests__/components/home/trending-section.test.tsx:448",
          "category": "Test Infrastructure",
          "effort_hours": 1,
          "impact_score": 5,
          "priority": "high",
          "status": "pending",
          "blockers": [],
          "files_affected": [
            "src/__tests__/components/home/trending-section.test.tsx"
          ],
          "related_docs": [
            "docs/operations/todo.md"
          ],
          "tags": [
            "test",
            "flaky"
          ],
          "created_at": "2025-12-23",
          "last_updated": "2026-01-25"
        }
      ]
    }
  ],
  "statistics": {
    "total_tasks": 286,
    "ready_to_start": 138,
    "blocked": 0,
    "in_progress": 0,
    "completed": 148,
    "total_effort_hours": 4.5
  },
  "recent_git_activity": [
    "2a0fda04 feat: add comprehensive Upstash data analysis and cleanup scripts",
    "c1d8924c feat: migrate from standard Redis client to Upstash Redis client",
    "f6b3cb67 feat: implement agent delegation and validation scripts; optimize MCP configurations",
    "6b3fe27b fix: properly gitignore all private/ directories",
    "7f56a5dc docs: update private files to TLP:AMBER classification",
    "0ea456d4 fix(docs): convert TLP tag to HTML comment in animation-decision-matrix.md",
    "6e845f70 fix(docs): add TLP tags and improve TLP validation",
    "b2ed0bd4 fix: update documentation placement validation in pre-commit hook",
    "2ffcf034 docs(governance): enforce operational documentation placement policy",
    "5de79181 Merge branch 'preview' of https://github.com/dcyfr/dcyfr-labs into preview"
  ]
}